Metadata-Version: 2.1
Name: sublime-backup
Version: 0.2
Summary: A simple command line tool to backup / sync your sublime snippets
Home-page: https://github.com/nishantwrp/sublime-backup-cli
Author: nishantwrp
Author-email: mittalnishant14@outlook.com
License: Apache 2.0
Platform: UNKNOWN
